MANIFEST.in
setup.py
quiver_engine/__init__.py
quiver_engine/imagenet_utils.py
quiver_engine/layer_result_generators.py
quiver_engine/server.py
quiver_engine/util.py
quiver_engine.egg-info/PKG-INFO
quiver_engine.egg-info/SOURCES.txt
quiver_engine.egg-info/dependency_links.txt
quiver_engine.egg-info/requires.txt
quiver_engine.egg-info/top_level.txt
quiver_engine/quiverboard/dist/app.14b8092d6ea379715007.js
quiver_engine/quiverboard/dist/app.c1d3d21cfba8c1aabed6806773c8f0ba.css
quiver_engine/quiverboard/dist/favicon.ico
quiver_engine/quiverboard/dist/humans.txt
quiver_engine/quiverboard/dist/index.html
quiver_engine/quiverboard/dist/robots.txt
quiver_engine/quiverboard/dist/vendor.280c5ce1d78077ee8d66.js